pyscanline/__init__.py
pyscanline/core.py
pyscanline-0.1.4.dist-info/METADATA
pyscanline-0.1.4.dist-info/WHEEL
pyscanline-0.1.4.dist-info/licenses/LICENSE
pyscanline-0.1.4.dist-info/RECORD
