Metadata-Version: 2.4
Name: pyscanline
Version: 0.1.4
Summary: A Python-based library that recreates a retro-futuristic style
Project-URL: Repository, https://github.com/onukura/pyscanline
Project-URL: Documentation, https://github.com/onukura/pyscanline
Project-URL: Releases, https://github.com/onukura/pyscanline/releases
Project-URL: Issues, https://github.com/onukura/pyscanline/issues
Author-email: onukura <26293997+onukura@users.noreply.github.com>
License: GNU General Public License
License-File: LICENSE
Keywords: Imaging
Classifier: Development Status :: 4 - Beta
Classifier: Intended Audience :: Developers
Classifier: License :: OSI Approved :: GNU General Public License v3 (GPLv3)
Classifier: Operating System :: OS Independent
Classifier: Programming Language :: Python
Classifier: Programming Language :: Python :: 3 :: Only
Classifier: Programming Language :: Python :: 3.10
Classifier: Programming Language :: Python :: 3.11
Classifier: Programming Language :: Python :: 3.12
Classifier: Programming Language :: Python :: 3.13
Classifier: Topic :: Multimedia :: Graphics :: Graphics Conversion
Classifier: Topic :: Scientific/Engineering :: Image Processing
Requires-Python: <3.14,>=3.10
Requires-Dist: imageio<3,>=2
Requires-Dist: matplotlib<4,>=3
Requires-Dist: numpy<3,>=1
Requires-Dist: pillow<12,>=10
